CHANGES.txt
COPYRIGHT.txt
LICENSE.txt
MANIFEST.in
README.txt
bootstrap.py
buildout.cfg
setup.py
tox.ini
src/zope/__init__.py
src/zope.apidoc.egg-info/PKG-INFO
src/zope.apidoc.egg-info/SOURCES.txt
src/zope.apidoc.egg-info/dependency_links.txt
src/zope.apidoc.egg-info/namespace_packages.txt
src/zope.apidoc.egg-info/not-zip-safe
src/zope.apidoc.egg-info/requires.txt
src/zope.apidoc.egg-info/top_level.txt
src/zope/apidoc/README.txt
src/zope/apidoc/__init__.py
src/zope/apidoc/classregistry.py
src/zope/apidoc/classregistry.txt
src/zope/apidoc/component.py
src/zope/apidoc/component.txt
src/zope/apidoc/interface.py
src/zope/apidoc/interface.txt
src/zope/apidoc/presentation.py
src/zope/apidoc/presentation.txt
src/zope/apidoc/sample.pt
src/zope/apidoc/tests.py
src/zope/apidoc/utilities.py
src/zope/apidoc/utilities.txt